logger/__init__.py
theme/__init__.py
theme/exceptions.py
spiffyline_snakeyworm-0.0.1.dist-info/LICENSE
spiffyline_snakeyworm-0.0.1.dist-info/METADATA
spiffyline_snakeyworm-0.0.1.dist-info/WHEEL
spiffyline_snakeyworm-0.0.1.dist-info/top_level.txt
spiffyline_snakeyworm-0.0.1.dist-info/RECORD
